pyfer/__init__.py
pyfer/pyfer.py
pyfer-4.1.0.dist-info/LICENSE.txt
pyfer-4.1.0.dist-info/METADATA
pyfer-4.1.0.dist-info/WHEEL
pyfer-4.1.0.dist-info/top_level.txt
pyfer-4.1.0.dist-info/RECORD
