Metadata-Version: 2.1
Name: pyfer
Version: 4.1.0
Summary: Simple string encryption
Home-page: https://github.com/elbydata/pyfer
Author: Elby Data
Author-email: info@elbydata.com
License: UNKNOWN
Platform: UNKNOWN
Classifier: Programming Language :: Python :: 3
Classifier: License :: OSI Approved :: MIT License
Classifier: Operating System :: OS Independent
Requires-Python: >=3.6
